{
  "checkpoint": "checkpoints/best.pt",
  "dataset": "CIFAR-100",
  "model": "CLIP ViT-B/32 + LoRA (rank=64)",
  "attack": {
    "type": "PGD",
    "epsilon": "4/255",
    "step_size": "1/255",
    "num_steps": 10
  },
  "results": {
    "id_accuracy": 85.37,
    "adversarial_accuracy_pgd": 37.10,
    "ood_avg_severity5": 55.54,
    "harmonic_mean_id_adv": 51.72,
    "harmonic_mean_3way": 52.94
  },
  "ood_per_corruption_severity5": {
    "gaussian_noise": 35.14,
    "shot_noise": 37.55,
    "impulse_noise": 20.95,
    "defocus_blur": 65.38,
    "glass_blur": 53.54,
    "motion_blur": 62.67,
    "zoom_blur": 69.60,
    "snow": 69.42,
    "frost": 70.83,
    "fog": 46.86,
    "brightness": 76.98,
    "contrast": 17.31,
    "elastic_transform": 68.39,
    "pixelate": 70.32,
    "jpeg_compression": 68.10
  },
  "training": {
    "epochs": 50,
    "batch_size": 256,
    "lr": 2e-4,
    "lambda_LAR": 1.0,
    "lambda_GV": 1.0,
    "awp_rho": 0.05,
    "awp_max_rank": 4,
    "curvature_K": 1000,
    "curvature_percentile": 0.8
  }
}
